MANIFEST.in
README.rst
setup.cfg
setup.py
tw2/__init__.py
tw2.jqplugins.elrte.egg-info/PKG-INFO
tw2.jqplugins.elrte.egg-info/SOURCES.txt
tw2.jqplugins.elrte.egg-info/dependency_links.txt
tw2.jqplugins.elrte.egg-info/entry_points.txt
tw2.jqplugins.elrte.egg-info/namespace_packages.txt
tw2.jqplugins.elrte.egg-info/not-zip-safe
tw2.jqplugins.elrte.egg-info/requires.txt
tw2.jqplugins.elrte.egg-info/top_level.txt
tw2/jqplugins/__init__.py
tw2/jqplugins/elrte/__init__.py
tw2/jqplugins/elrte/base.py
tw2/jqplugins/elrte/defaults.py
tw2/jqplugins/elrte/samples.py
tw2/jqplugins/elrte/widgets.py
tw2/jqplugins/elrte/static/jquery/plugins/elrte/1.2/Changelog
tw2/jqplugins/elrte/static/jquery/plugins/elrte/1.2/README
tw2/jqplugins/elrte/static/jquery/plugins/elrte/1.2/elrte-1.2.tar.gz
tw2/jqplugins/elrte/static/jquery/plugins/elrte/1.2/elrte.html
tw2/jqplugins/elrte/static/jquery/plugins/elrte/1.2/css/elrte-inner.css
tw2/jqplugins/elrte/static/jquery/plugins/elrte/1.2/css/elrte.full.css
tw2/jqplugins/elrte/static/jquery/plugins/elrte/1.2/css/elrte.min.css
tw2/jqplugins/elrte/static/jquery/plugins/elrte/1.2/css/smoothness/jquery-ui-1.8.7.custom.css
tw2/jqplugins/elrte/static/jquery/plugins/elrte/1.2/css/smoothness/images/ui-bg_flat_0_aaaaaa_40x100.png
tw2/jqplugins/elrte/static/jquery/plugins/elrte/1.2/css/smoothness/images/ui-bg_flat_75_ffffff_40x100.png
tw2/jqplugins/elrte/static/jquery/plugins/elrte/1.2/css/smoothness/images/ui-bg_glass_55_fbf9ee_1x400.png
tw2/jqplugins/elrte/static/jquery/plugins/elrte/1.2/css/smoothness/images/ui-bg_glass_65_ffffff_1x400.png
tw2/jqplugins/elrte/static/jquery/plugins/elrte/1.2/css/smoothness/images/ui-bg_glass_75_dadada_1x400.png
tw2/jqplugins/elrte/static/jquery/plugins/elrte/1.2/css/smoothness/images/ui-bg_glass_75_e6e6e6_1x400.png
tw2/jqplugins/elrte/static/jquery/plugins/elrte/1.2/css/smoothness/images/ui-bg_glass_95_fef1ec_1x400.png
tw2/jqplugins/elrte/static/jquery/plugins/elrte/1.2/css/smoothness/images/ui-bg_highlight-soft_75_cccccc_1x100.png
tw2/jqplugins/elrte/static/jquery/plugins/elrte/1.2/css/smoothness/images/ui-icons_222222_256x240.png
tw2/jqplugins/elrte/static/jquery/plugins/elrte/1.2/css/smoothness/images/ui-icons_2e83ff_256x240.png
tw2/jqplugins/elrte/static/jquery/plugins/elrte/1.2/css/smoothness/images/ui-icons_454545_256x240.png
