Metadata-Version: 1.0
Name: tw2.jqplugins.elrte
Version: 2.0b10
Summary: toscawidgets2 wrapper for elRTE
Home-page: http://github.com/ralphbean/tw2.jqplugins.elrte
Author: Joseph Tate
Author-email: jtate@dragonstrider.com
License: MIT
Keywords: toscawidgets.widgets
Platform: UNKNOWN
Classifier: Development Status :: 3 - Alpha
Classifier: Environment :: Web Environment
Classifier: Environment :: Web Environment :: ToscaWidgets
Classifier: Topic :: Software Development :: Libraries :: Python Modules
Classifier: Topic :: Software Development :: Widget Sets
Classifier: Intended Audience :: Developers
Classifier: Operating System :: OS Independent
Classifier: Programming Language :: Python
Classifier: Programming Language :: JavaScript
